ipcpy/__init__.py
ipcpy/ip.py
ipcpy/message.py
ipcpy/udpsocket.py
ipcpy-2024.11.26.1.dist-info/METADATA
ipcpy-2024.11.26.1.dist-info/WHEEL
ipcpy-2024.11.26.1.dist-info/RECORD
