Metadata-Version: 2.1
Name: ipcpy
Version: 2024.11.26.1
Summary: A interprocess communications (IPC) framework using UDP
Home-page: https://pypi.org/project/ipcpy/
License: MIT
Keywords: udp,ipc,interprocess communication
Author: walchko
Author-email: walchko@users.noreply.github.com
Requires-Python: >=3.10
Classifier: Development Status :: 4 - Beta
Classifier: Intended Audience :: Developers
Classifier: License :: OSI Approved :: MIT License
Classifier: Operating System :: OS Independent
Classifier: Programming Language :: Python :: 3
Classifier: Programming Language :: Python :: 3.10
Classifier: Programming Language :: Python :: 3.11
Classifier: Programming Language :: Python :: 3.12
Classifier: Programming Language :: Python :: 3.13
Classifier: Topic :: Software Development :: Libraries
Classifier: Topic :: Software Development :: Libraries :: Application Frameworks
Classifier: Topic :: Software Development :: Libraries :: Python Modules
Project-URL: Repository, https://github.com/MomsFriendlyRobotCompany/ipc/python
